geoitapy/__init__.py
geoitapy/db_manager.py
geoitapy/exceptions.py
geoitapy/functions.py
geoitapy/util.py
geoitapy/api/__init__.py
geoitapy/api/db_manager.py
geoitapy/api/exceptions.py
geoitapy/api/functions.py
geoitapy-0.1.7.dist-info/LICENSE
geoitapy-0.1.7.dist-info/METADATA
geoitapy-0.1.7.dist-info/WHEEL
geoitapy-0.1.7.dist-info/top_level.txt
geoitapy-0.1.7.dist-info/RECORD
