Metadata-Version: 2.1
Name: geoitapy
Version: 0.1.7
Summary: Python Geocoding Toolbox for Italy
Home-page: https://github.com/mett96/geoitapy
Author: Mattia Sanchioni
Author-email: mattia.sanchioni.dev@gmail.com
License: UNKNOWN
Platform: UNKNOWN
Classifier: Intended Audience :: Science/Research
Classifier: Intended Audience :: Developers
Classifier: License :: OSI Approved :: MIT License
Classifier: Programming Language :: Python
Classifier: Programming Language :: Python :: 3
Classifier: Programming Language :: Python :: 3.6
Classifier: Programming Language :: Python :: 3.7
Classifier: Programming Language :: Python :: 3.8
Classifier: Programming Language :: Python :: 3.9
Classifier: Topic :: Software Development
Classifier: Operating System :: OS Independent
Classifier: Operating System :: POSIX
Classifier: Operating System :: Unix
Classifier: Development Status :: 1 - Planning
Requires-Python: >=3.6
Requires-Dist: loggerpy
Requires-Dist: pandas
Requires-Dist: numpy
